toast/__init__.py
toast/__main__.py
toast/helpers.py
toast/plugins/__init__.py
toast/plugins/am_plugin.py
toast/plugins/base_plugin.py
toast/plugins/cdw_plugin.py
toast/plugins/ctx_plugin.py
toast/plugins/dot_plugin.py
toast/plugins/env_plugin.py
toast/plugins/git_plugin.py
toast/plugins/prompt_plugin.py
toast/plugins/region_plugin.py
toast/plugins/ssm_plugin.py
toast/plugins/utils.py
toast_cli-4.0.2.dist-info/licenses/LICENSE
toast_cli-4.0.2.dist-info/METADATA
toast_cli-4.0.2.dist-info/WHEEL
toast_cli-4.0.2.dist-info/entry_points.txt
toast_cli-4.0.2.dist-info/top_level.txt
toast_cli-4.0.2.dist-info/RECORD
